wx_ocr/__init__.py
wx_ocr/cli.py
wx_ocr/default_callback.py
wx_ocr/mmmojo_dll.py
wx_ocr/ocr_manager.py
wx_ocr/ocr_protobuf_pb2.py
wx_ocr/simple_api.py
wx_ocr/utility_protobuf_pb2.py
wx_ocr/utils.py
wx_ocr/winapi.py
wx_ocr/xplugin_manager.py
wx_ocr/wco_data/WeChatOCR.exe
wx_ocr/wco_data/mmmojo.dll
wx_ocr/wco_data/mmmojo_64.dll
wx_ocr/wco_data/x64.config
wx_ocr/wco_data/Model/FPOCRRecog.xnet
wx_ocr/wco_data/Model/OCRDetFP32.xnet.nas
wx_ocr/wco_data/Model/OCRParaDetV1.1.0.26.xnet
wx_ocr/wco_data/Model/OCRRecogFP32V1.1.0.26.xnet
wx_ocr/wco_data/Model/RecDict
wx_ocr/wco_data/Model/sohu_simp.txt
wx_ocr-0.1.6.dist-info/licenses/LICENSE
wx_ocr-0.1.6.dist-info/METADATA
wx_ocr-0.1.6.dist-info/WHEEL
wx_ocr-0.1.6.dist-info/entry_points.txt
wx_ocr-0.1.6.dist-info/top_level.txt
wx_ocr-0.1.6.dist-info/RECORD
