Metadata-Version: 2.4
Name: wx-ocr
Version: 0.1.6
Summary: 超级简单的微信 OCR - 一行代码识别图片文字 | Super simple WeChat OCR
Author: wx-ocr contributors
License: MIT
Project-URL: Original Project, https://github.com/kanadeblisst00/wechat_ocr
Keywords: wechat,ocr,text-recognition,image-processing,微信,文字识别,wx
Classifier: Development Status :: 4 - Beta
Classifier: Intended Audience :: Developers
Classifier: License :: OSI Approved :: MIT License
Classifier: Operating System :: Microsoft :: Windows
Classifier: Programming Language :: Python :: 3
Classifier: Programming Language :: Python :: 3.8
Classifier: Programming Language :: Python :: 3.9
Classifier: Programming Language :: Python :: 3.10
Classifier: Programming Language :: Python :: 3.11
Classifier: Programming Language :: Python :: 3.12
Classifier: Programming Language :: Python :: 3.13
Classifier: Topic :: Multimedia :: Graphics :: Capture :: Screen Capture
Classifier: Topic :: Scientific/Engineering :: Image Recognition
Requires-Python: >=3.8
License-File: LICENSE
Requires-Dist: protobuf>=3.20.0
Dynamic: license-file
